llms_from_scratch/__init__.py
llms_from_scratch/appendix_a.py
llms_from_scratch/appendix_d.py
llms_from_scratch/appendix_e.py
llms_from_scratch/ch02.py
llms_from_scratch/ch03.py
llms_from_scratch/ch04.py
llms_from_scratch/ch05.py
llms_from_scratch/ch06.py
llms_from_scratch/ch07.py
llms_from_scratch/generate.py
llms_from_scratch/llama3.py
llms_from_scratch/qwen3.py
llms_from_scratch/utils.py
llms_from_scratch/kv_cache/__init__.py
llms_from_scratch/kv_cache/generate.py
llms_from_scratch/kv_cache/gpt2.py
llms_from_scratch/kv_cache/llama3.py
llms_from_scratch/kv_cache/qwen3.py
llms_from_scratch/kv_cache/utils.py
llms_from_scratch/kv_cache_batched/__init__.py
llms_from_scratch/kv_cache_batched/generate.py
llms_from_scratch/kv_cache_batched/qwen3.py
llms_from_scratch/kv_cache_batched/utils.py
llms_from_scratch/tests/test_appendix_a.py
llms_from_scratch/tests/test_appendix_d.py
llms_from_scratch/tests/test_appendix_e.py
llms_from_scratch/tests/test_ch02.py
llms_from_scratch/tests/test_ch03.py
llms_from_scratch/tests/test_ch04.py
llms_from_scratch/tests/test_ch05.py
llms_from_scratch/tests/test_ch06.py
llms_from_scratch/tests/test_ch07.py
llms_from_scratch/tests/test_generate.py
llms_from_scratch/tests/test_llama3.py
llms_from_scratch/tests/test_qwen3.py
llms_from_scratch-1.0.19.dist-info/licenses/LICENSE.txt
llms_from_scratch-1.0.19.dist-info/METADATA
llms_from_scratch-1.0.19.dist-info/WHEEL
llms_from_scratch-1.0.19.dist-info/top_level.txt
llms_from_scratch-1.0.19.dist-info/RECORD
