Metadata-Version: 2.4
Name: llms-from-scratch
Version: 1.0.19
Summary: Implement a ChatGPT-like LLM in PyTorch from scratch, step by step
Requires-Python: <=3.13,>=3.10
License-File: LICENSE.txt
Requires-Dist: torch<2.6,>=2.2.2; sys_platform == "darwin" and platform_machine == "x86_64" and python_version < "3.13"
Requires-Dist: torch>=2.2.2; sys_platform == "darwin" and platform_machine == "arm64"
Requires-Dist: torch>=2.2.2; sys_platform == "linux"
Requires-Dist: torch>=2.2.2; sys_platform == "win32"
Requires-Dist: tensorflow>=2.16.2; sys_platform == "darwin" and platform_machine == "x86_64"
Requires-Dist: tensorflow>=2.18.0; sys_platform == "darwin" and platform_machine == "arm64"
Requires-Dist: tensorflow>=2.18.0; sys_platform == "linux"
Requires-Dist: tensorflow>=2.18.0; sys_platform == "win32"
Requires-Dist: jupyterlab>=4.0
Requires-Dist: tiktoken>=0.5.1
Requires-Dist: matplotlib>=3.7.1
Requires-Dist: tqdm>=4.66.1
Requires-Dist: numpy<2.1,>=1.26
Requires-Dist: pandas>=2.2.1
Requires-Dist: pip>=25.0.1
Requires-Dist: pytest>=8.3.5
Dynamic: license-file
